subcalc/__init__.py
subcalc/main.py
subcalc-0.1.0.dist-info/LICENSE
subcalc-0.1.0.dist-info/METADATA
subcalc-0.1.0.dist-info/WHEEL
subcalc-0.1.0.dist-info/entry_points.txt
subcalc-0.1.0.dist-info/RECORD
