Metadata-Version: 2.3
Name: subcalc
Version: 0.1.0
Summary: A network subnet calculator
License: MIT
Author: Craig
Author-email: ceaveson@gmail.com
Requires-Python: >=3.10,<4.0.0
Classifier: Programming Language :: Python :: 3
Classifier: Operating System :: OS Independent
Requires-Dist: textual (>=6.2.1,<7.0.0)
Project-URL: Homepage, https://github.com/ceaveson/subcalc
